npi/__init__.py
npi/pyfind.py
numpy_illustrated-0.3.1.dist-info/LICENSE.txt
numpy_illustrated-0.3.1.dist-info/METADATA
numpy_illustrated-0.3.1.dist-info/WHEEL
numpy_illustrated-0.3.1.dist-info/top_level.txt
numpy_illustrated-0.3.1.dist-info/RECORD
