Metadata-Version: 2.1
Name: numpy-illustrated
Version: 0.3.1
Summary: Helper functions from the NumPy Illustrated guide
Home-page: https://github.com/axil/numpy-illustrated
Author: Lev Maximov
Author-email: lev.maximov@gmail.com
License: MIT License
Keywords: find,argmin,argmax,sort,irange,numpy,first_above,first_nonzero
Platform: UNKNOWN
Classifier: Development Status :: 4 - Beta
Classifier: License :: OSI Approved :: MIT License
Classifier: Operating System :: OS Independent
Classifier: Programming Language :: Python :: 3.8
Classifier: Programming Language :: Python :: 3.9
Classifier: Programming Language :: Python :: 3.10
Classifier: Programming Language :: Python :: 3.11
Requires-Python: >=3.7
License-File: LICENSE.txt
Requires-Dist: numpy
